cpgqls_client/__init__.py
cpgqls_client/client.py
cpgqls_client/queries.py
cpgqls_client-0.0.9.dist-info/LICENSE
cpgqls_client-0.0.9.dist-info/METADATA
cpgqls_client-0.0.9.dist-info/WHEEL
cpgqls_client-0.0.9.dist-info/top_level.txt
cpgqls_client-0.0.9.dist-info/RECORD
