Metadata-Version: 2.1
Name: cpgqls-client
Version: 0.0.9
Summary: A client library for CPGQL servers
Home-page: https://github.com/joernio/cpgqls-client-python
Author: ShiftLeft Inc.
Author-email: claudiu@shiftleft.io
License: UNKNOWN
Platform: UNKNOWN
Classifier: Programming Language :: Python :: 3.7
Classifier: Programming Language :: Python :: 3.8
Classifier: Programming Language :: Python :: 3.9
Classifier: License :: OSI Approved :: Apache Software License
Classifier: Operating System :: OS Independent
Requires-Python: >=3.7
Requires-Dist: requests (>=2.25.1)
Requires-Dist: websockets (>=9.1)
